{
    "ServerName": "",
    "ButtonTxt1": "Информация",
    "ButtonTxt2": "Дополнительная информация",
    "ButtonTxt3": "",
    "ButtonTxt4": "",
    "ButtonTxt5": "",
    "LinkButtonTxt1": "Магазин",
    "LinkButtonTxt2": "Вконтакте",
    "LinkButtonTxt3": "Discord",
    "LinkButtonTxt4": "Моды",
    "LinkButtonTxt5": "Правила",
    "LinkButton1": "https://arkliberty-x5.survivalshop.org",
    "LinkButton2": "https://vk.com/arkliberty",
    "Link1Button3": "https://discordapp.com/invite/SJEMqFR",
    "Link2Button3": "",
    "Link3Button3": "",
    "Link4Button3": "",
    "Link1Button4": "https://steamcommunity.com/sharedfiles/filedetails/?id=2965437901",
    "Link2Button4": "",
    "Link3Button4": "",
    "Link4Button4": "",
    "Link1Button5": "https://vk.com/topic-170842015_39276808",
    "Link2Button5": "",
    "Link3Button5": "",
    "Link4Button5": "",
    "Tab1Panelcount": 2,
    "Tab2Panelcount": 2,
    "Tab3Panelcount": 1,
    "Tab4Panelcount": 1,
    "Tab5Panelcount": 1,
    "BackgroundTab1": 14,
    "BackgroundTab2": 14,
    "BackgroundTab3": 14,
    "BackgroundTab4": 14,
    "BackgroundTab5": 14,
    "Background3Color": "0,0,255,0.5",
    "FontColorButtons": "255,255,255",
    "FontColorServerName": "255,95,0",
    "FontColorTabTitles": "20,255,0",
    "FontColorTabText": "255,255,255",
    "UseSteamBrowserLink1": false,
    "UseSteamBrowserLink2": false,
    "Tab1Title1": "Информация о проекте ARKLiberty:",
    "Tab1Title2": "Наcтройки PvE кластера x5:",
    "Tab1Title3": "",
    "Tab2Title1": "Очки начисляются по 50 очков раз в 30 минут!",
    "Tab2Title2": "Дополнительные настройки",
    "Tab2Title3": "",
    "Tab3Title1": "",
    "Tab3Title2": "",
    "Tab3Title3": "",
    "Tab4Title1": "",
    "Tab4Title2": "",
    "Tab4Title3": "",
    "Tab5Title1": "",
    "Tab5Title2": "",
    "Tab5Title3": "",
    "Tab1Text1": "
Кластер PvE серверов с рейтами х5:
----------------------------------------------------------------------------------------------
За игру на сервере начисляются очки. С помощью очков можно пользоваться внутриигровым магазином на F11!
----------------------------------------------------------------------------------------------
Всех животных можно переносить на Aberration, но нельзя оседлать летунов и некоторых больших животных!
----------------------------------------------------------------------------------------------

[RU] ARKLiberty x5 Ragnarok [PvE]
188.255.118.122:27015

[RU] ARKLiberty x5 TheIsland [PvE]
188.255.118.122:27020

[RU] ARKLiberty x5 Aberration [PvE]
188.255.118.122:27025

[RU] ARKLiberty x5 Extinction [PvE]
188.255.118.122:27030

[RU] ARKLiberty x5 CrystalIsles [PvE]
188.255.118.122:27035

[RU] ARKLiberty x5 Genesis [PvE]
188.255.118.122:27040

[RU] ARKLiberty x5 Fjordur [PvE]
188.255.118.122:27045

[RU] ARKLiberty x5 Genesis2 [PvE]
188.255.118.122:27050

",
    "Tab1Text2": "
Опыт - х5
Приручение - х5
Сбор ресурсов - x5 (не на всё)
Рост грядок - х5
Выращивание - х5
Инкубация - х5
Скорость спаривания - х5
Качество лута в контейнерах/рыбалке - х1.2/х1.5
Количество турелей в радиусе - 100 шт
Максимальный уровень игрока - 105 + 80 (чиби и пять вознесений) + 20 (заметки и руны)
Максимальный уровень диких животных - 150
Максимальный уровень яиц виверн, дрейков и дейнонихов - 190
Максимальный прокачиваемый уровень дино +88
Лимит животных на трайб - 200
Общий лимит на сервере - 5000
Полёт в пещерах - откл
Бесконечное использование Амнезии - вкл
Расположение игрока на мини карте - вкл
Вид от 3 лица - вкл
Луч для поиска трупов - вкл
Отображение урона - вкл
Гамма - вкл
Коллизия текстур - откл
Автозапирание построек - вкл
Старение и саморазрушение построек - вкл
Несвязанные постройки разрушаются через 30 минут
Количество человек в трайбе - 20
Альянсы - вкл
----------------------------------------------------------------------------------------------
Поуровневые множители персонажа:
  Выносливость - х3
  Стойкость - х3
  Вес - х3
  Скорость - х2
----------------------------------------------------------------------------------------------
Поуровневые множители животных:
  Выносливость - х5
  Вес - х5
  Скорость - х1.5
",
    "Tab1Text3": "",
    "Tab2Text1": "
Список всех товаров можно посмотреть, открыв магазин на F11.

Животные не кастрированы!

«Стартовый набор» начисляется автоматически после первого входа на один из серверов. Если вы уже играли у нас раньше, то вам надо покупать набор за очки.
",
    "Tab2Text2": "
Настройки Мутатора:
  Мутация (Mutation) - 200 элемента
  Поменять пол (Gender Swap) - 300 элемента
  Случайный пол (Gender Assignment) - 100 элемента
  Разрешить размножение (Allow Breeding) - 300 элемента
  Привязка (Imprint) - откл
  Остановить рост дино (Age Freeze) - 100 элемента
  Ускорение роста (Boost Growth) - откл
----------------------------------------------------------------------------------------------
Список летающих животных на карте Genesis 1:
  Аргентавис, Х-Аргентавис, Пелагорнис, Птеранодон, Тапежара, Х-Тапежара, Тропеогнат, Манагарм, Дрейк и Майвинг.
----------------------------------------------------------------------------------------------
Всех животных можно переносить на Aberration, но нельзя оседлать летунов и некоторых больших животных.
----------------------------------------------------------------------------------------------
Старение структур:
  Солома - 4 дня, Дерево и Саман - 8 дней, Камень - 12 дней, Теплица - 15 дней, Металл/Шкафы/Животные - 16 дней, Тек - 20 дней
  Несвязанные постройки разрушаются через 24 часа
----------------------------------------------------------------------------------------------
  Команды для чата в игре:
1. /suicide - покончить с собой, если застряли (нельзя использовать в лапах, сидя на животном, лёжа на кровати или без сознания)
2. /groups - посмотреть сколько осталось часов до конца премиума, приобретённого в донат магазине
3. /giveengrams - выучить все энграммы, доступные на данный момент (изучение на свой страх и риск, при переходе на другой сервер может быть ошибка Outgoing Reliable Buffer Overflow)
4. /sl - узнать лимит структур на трайб
5. /dl - узнать лимит дино на трайб
",
    "Tab2Text3": "",
    "Tab3Text1": "",
    "Tab3Text2": "",
    "Tab3Text3": "",
    "Tab4Text1": "",
    "Tab4Text2": "",
    "Tab4Text3": "",
    "Tab5Text1": "",
    "Tab5Text2": "",
    "Tab5Text3": ""
}
